{
  "data": {
    "article": {},
    "attachments": {},
    "author_id": "1620506107306479617",
    "conversation_id": "1928133356622844294",
    "created_at": "2025-05-29T17:23:28.000Z",
    "edit_controls": {
      "editable_until": "2025-05-29T18:23:28.000Z",
      "edits_remaining": 5,
      "is_edit_eligible": false
    },
    "edit_history_tweet_ids": [
      "1928140145561047183"
    ],
    "entities": {
      "mentions": [
        {
          "end": 16,
          "id": "1815292939901493248",
          "start": 0,
          "username": "lovcatcommunity"
        }
      ],
      "urls": [
        {
          "description": "MtF.wiki is committed to becoming a free, open, and continuously updated transgender knowledge integration site.",
          "display_url": "mtf.wiki/zh-cn/",
          "end": 40,
          "expanded_url": "https://mtf.wiki/zh-cn/",
          "start": 17,
          "status": 200,
          "title": "MtF.wiki",
          "unwound_url": "https://mtf.wiki/zh-cn/",
          "url": "https://t.co/yR03p2NKSx"
        }
      ]
    },
    "geo": {},
    "id": "1928140145561047183",
    "in_reply_to_user_id": "1815292939901493248",
    "lang": "zh",
    "note_tweet": {
      "entities": {}
    },
    "possibly_sensitive": false,
    "public_metrics": {
      "bookmark_count": 0,
      "impression_count": 0,
      "like_count": 0,
      "quote_count": 0,
      "reply_count": 0,
      "retweet_count": 0
    },
    "referenced_tweets": [
      {
        "id": "1928133356622844294",
        "type": "replied_to"
      }
    ],
    "reply_settings": "everyone",
    "text": "@lovcatcommunity https://t.co/yR03p2NKSx\n宝宝不要乱吃哦，建议制订一个适合自己的用药方案😘"
  },
  "includes": {
    "media": [
      {
        "height": 960,
        "media_key": "3_1928133289925107712",
        "public_metrics": {},
        "type": "photo",
        "url": "https://pbs.twimg.com/media/GsIbAvGXYAAZXsb.jpg",
        "width": 1280
      }
    ],
    "tweets": [
      {
        "article": {},
        "attachments": {},
        "author_id": "1620506107306479617",
        "conversation_id": "1928133356622844294",
        "created_at": "2025-05-29T17:23:28.000Z",
        "edit_controls": {
          "editable_until": "2025-05-29T18:23:28.000Z",
          "edits_remaining": 5,
          "is_edit_eligible": false
        },
        "edit_history_tweet_ids": [
          "1928140145561047183"
        ],
        "entities": {
          "mentions": [
            {
              "end": 16,
              "id": "1815292939901493248",
              "start": 0,
              "username": "lovcatcommunity"
            }
          ],
          "urls": [
            {
              "description": "MtF.wiki is committed to becoming a free, open, and continuously updated transgender knowledge integration site.",
              "display_url": "mtf.wiki/zh-cn/",
              "end": 40,
              "expanded_url": "https://mtf.wiki/zh-cn/",
              "start": 17,
              "status": 200,
              "title": "MtF.wiki",
              "unwound_url": "https://mtf.wiki/zh-cn/",
              "url": "https://t.co/yR03p2NKSx"
            }
          ]
        },
        "geo": {},
        "id": "1928140145561047183",
        "in_reply_to_user_id": "1815292939901493248",
        "lang": "zh",
        "note_tweet": {
          "entities": {}
        },
        "possibly_sensitive": false,
        "public_metrics": {
          "bookmark_count": 0,
          "impression_count": 0,
          "like_count": 0,
          "quote_count": 0,
          "reply_count": 0,
          "retweet_count": 0
        },
        "referenced_tweets": [
          {
            "id": "1928133356622844294",
            "type": "replied_to"
          }
        ],
        "reply_settings": "everyone",
        "text": "@lovcatcommunity https://t.co/yR03p2NKSx\n宝宝不要乱吃哦，建议制订一个适合自己的用药方案😘"
      },
      {
        "article": {},
        "attachments": {
          "media_keys": [
            "3_1928133289925107712"
          ]
        },
        "author_id": "1815292939901493248",
        "conversation_id": "1928133356622844294",
        "created_at": "2025-05-29T16:56:29.000Z",
        "edit_controls": {
          "editable_until": "2025-05-29T17:56:29.000Z",
          "edits_remaining": 5,
          "is_edit_eligible": true
        },
        "edit_history_tweet_ids": [
          "1928133356622844294"
        ],
        "entities": {
          "urls": [
            {
              "display_url": "pic.x.com/ansHlzFBpD",
              "end": 176,
              "expanded_url": "https://x.com/lovcatcommunity/status/1928133356622844294/photo/1",
              "media_key": "3_1928133289925107712",
              "start": 153,
              "url": "https://t.co/ansHlzFBpD"
            }
          ]
        },
        "geo": {},
        "id": "1928133356622844294",
        "lang": "zh",
        "note_tweet": {
          "entities": {}
        },
        "possibly_sensitive": false,
        "public_metrics": {
          "bookmark_count": 0,
          "impression_count": 51,
          "like_count": 1,
          "quote_count": 0,
          "reply_count": 1,
          "retweet_count": 0
        },
        "reply_settings": "everyone",
        "text": "现在吃糖 是不是 太晚了\nnmud 买了一点 补佳乐\n还有 抗雄的\n\n准备开始 自己吃\nnmud 也不是 很懂\n\n因为 nmud 也没有钱\n只买了 一点\n便宜的 国补\n\n但是 nmud\n也不知道 怎么 开始吃\n有没有人 来指导下\n善良的 nmud\n\n先吃了 2mg\n含在嘴里 感觉 甜甜的\n好像 有点好吃 https://t.co/ansHlzFBpD"
      }
    ],
    "users": [
      {
        "created_at": "2023-01-31T19:36:01.000Z",
        "description": "幽灵狐狐与您同在~ 丨☯Survivalist 生存主義者 醫學學習預定 電子工程學精通🆙 丨MtX幽默没含糖男娘🏳️‍⚧️丨私人實驗室「靈狐製作所」創始人(建設ing…)丨長白山香煙與粉色魔爪愛好者 丨無政治傾向/尊重所有人 /超友好🥰丨良い世,来いよ! 丨裡推慎fo @HEX_Ghostfox",
        "entities": {
          "description": {
            "mentions": [
              {
                "end": 149,
                "start": 136,
                "username": "HEX_Ghostfox"
              }
            ]
          }
        },
        "id": "1620506107306479617",
        "location": "Turn around....(∞_눈)",
        "name": "芝士灵狐🧐(Hachimi Generator.ver)",
        "pinned_tweet_id": "1919548841357148382",
        "profile_image_url": "https://pbs.twimg.com/profile_images/1876362817898795008/xm_WN6Rd_normal.jpg",
        "protected": false,
        "public_metrics": {
          "followers_count": 225,
          "following_count": 416,
          "like_count": 2638,
          "listed_count": 0,
          "media_count": 131,
          "tweet_count": 975
        },
        "username": "Cheese_Ghostfox",
        "verified": false
      },
      {
        "created_at": "2024-07-22T07:49:18.000Z",
        "description": "#爱猫 #萌宠 #小猫  #好物推荐 #宠物冷知识\n大家好 这里是 爱猫社区 官方推特\n性别是3岁小猫\n喜欢的 食物 是 抹茶芭菲\n喜欢的 动物 是 毛绒绒 小伙伴\n会分享 宠物冷知识 好物推荐\n来到推特 目标是 是交 10000个 好朋友",
        "entities": {
          "description": {
            "hashtags": [
              {
                "end": 3,
                "start": 0,
                "tag": "爱猫"
              },
              {
                "end": 7,
                "start": 4,
                "tag": "萌宠"
              },
              {
                "end": 11,
                "start": 8,
                "tag": "小猫"
              },
              {
                "end": 18,
                "start": 13,
                "tag": "好物推荐"
              },
              {
                "end": 25,
                "start": 19,
                "tag": "宠物冷知识"
              }
            ]
          },
          "url": {
            "urls": [
              {
                "display_url": "aimaotv.com",
                "end": 23,
                "expanded_url": "https://www.aimaotv.com",
                "start": 0,
                "url": "https://t.co/nyLCsfqI0C"
              }
            ]
          }
        },
        "id": "1815292939901493248",
        "location": "Όλυμπος",
        "name": "爱猫社区 - 二周年",
        "pinned_tweet_id": "1923265607828390166",
        "profile_image_url": "https://pbs.twimg.com/profile_images/1928139370596352000/bvKrlXOq_normal.jpg",
        "protected": false,
        "public_metrics": {
          "followers_count": 865,
          "following_count": 132,
          "like_count": 33,
          "listed_count": 0,
          "media_count": 57,
          "tweet_count": 400
        },
        "url": "https://t.co/nyLCsfqI0C",
        "username": "lovcatcommunity",
        "verified": false
      }
    ]
  }
}