{
  "data": {
    "article": {},
    "attachments": {},
    "author_id": "1620506107306479617",
    "conversation_id": "1956786086681915725",
    "created_at": "2025-08-17T17:21:43.000Z",
    "edit_controls": {
      "editable_until": "2025-08-17T18:21:43.000Z",
      "edits_remaining": 5,
      "is_edit_eligible": false
    },
    "edit_history_tweet_ids": [
      "1957130734444990829"
    ],
    "entities": {
      "mentions": [
        {
          "end": 10,
          "id": "1819042830549204992",
          "start": 0,
          "username": "ss3996418"
        }
      ]
    },
    "geo": {},
    "id": "1957130734444990829",
    "in_reply_to_user_id": "1819042830549204992",
    "lang": "zh",
    "note_tweet": {
      "entities": {}
    },
    "possibly_sensitive": false,
    "public_metrics": {
      "bookmark_count": 0,
      "impression_count": 34,
      "like_count": 0,
      "quote_count": 0,
      "reply_count": 0,
      "retweet_count": 0
    },
    "referenced_tweets": [
      {
        "id": "1957100165262917787",
        "type": "replied_to"
      }
    ],
    "reply_settings": "everyone",
    "text": "@ss3996418 是语气，一位东北人会在与人对话时不由自主地起↑伏↓压↑声↓…\n然后就毫无抵抗地露出本音了😭\n这坏习惯必须改掉喵…"
  },
  "includes": {
    "tweets": [
      {
        "article": {},
        "attachments": {},
        "author_id": "1620506107306479617",
        "conversation_id": "1956786086681915725",
        "created_at": "2025-08-17T17:21:43.000Z",
        "edit_controls": {
          "editable_until": "2025-08-17T18:21:43.000Z",
          "edits_remaining": 5,
          "is_edit_eligible": false
        },
        "edit_history_tweet_ids": [
          "1957130734444990829"
        ],
        "entities": {
          "mentions": [
            {
              "end": 10,
              "id": "1819042830549204992",
              "start": 0,
              "username": "ss3996418"
            }
          ]
        },
        "geo": {},
        "id": "1957130734444990829",
        "in_reply_to_user_id": "1819042830549204992",
        "lang": "zh",
        "note_tweet": {
          "entities": {}
        },
        "possibly_sensitive": false,
        "public_metrics": {
          "bookmark_count": 0,
          "impression_count": 34,
          "like_count": 0,
          "quote_count": 0,
          "reply_count": 0,
          "retweet_count": 0
        },
        "referenced_tweets": [
          {
            "id": "1957100165262917787",
            "type": "replied_to"
          }
        ],
        "reply_settings": "everyone",
        "text": "@ss3996418 是语气，一位东北人会在与人对话时不由自主地起↑伏↓压↑声↓…\n然后就毫无抵抗地露出本音了😭\n这坏习惯必须改掉喵…"
      },
      {
        "article": {},
        "attachments": {},
        "author_id": "1819042830549204992",
        "conversation_id": "1956786086681915725",
        "created_at": "2025-08-17T15:20:15.000Z",
        "edit_controls": {
          "editable_until": "2025-08-17T16:20:15.000Z",
          "edits_remaining": 5,
          "is_edit_eligible": false
        },
        "edit_history_tweet_ids": [
          "1957100165262917787"
        ],
        "entities": {
          "mentions": [
            {
              "end": 16,
              "id": "1620506107306479617",
              "start": 0,
              "username": "Cheese_Ghostfox"
            }
          ]
        },
        "geo": {},
        "id": "1957100165262917787",
        "in_reply_to_user_id": "1620506107306479617",
        "lang": "zh",
        "note_tweet": {
          "entities": {}
        },
        "possibly_sensitive": false,
        "public_metrics": {
          "bookmark_count": 0,
          "impression_count": 3,
          "like_count": 1,
          "quote_count": 0,
          "reply_count": 1,
          "retweet_count": 0
        },
        "referenced_tweets": [
          {
            "id": "1956786086681915725",
            "type": "replied_to"
          }
        ],
        "reply_settings": "everyone",
        "text": "@Cheese_Ghostfox 是不是注意力有点分散了，"
      }
    ],
    "users": [
      {
        "created_at": "2023-01-31T19:36:01.000Z",
        "description": "幽灵狐狐与您同在~ 丨☯Survivalist 生存主義者 醫學/電子工程學🆙 丨INTP–T丨MtX幽默无证药娘(?)🏳️‍⚧️丨私人實驗室「靈狐製作所」創始人(建設ing…)🧬丨長白山香煙與粉色魔爪愛好者 丨無政治傾向 /超友好🥰丨燦若花火的生命，无法用只言片语概括丨裡推慎fo @HEX_Ghostfox",
        "entities": {
          "description": {
            "mentions": [
              {
                "end": 155,
                "start": 142,
                "username": "HEX_Ghostfox"
              }
            ]
          }
        },
        "id": "1620506107306479617",
        "location": "Turn around....(∞_눈)",
        "name": "☯🧬霊狐製作所 公式ツイッター🏳️‍⚧️",
        "pinned_tweet_id": "1919548841357148382",
        "profile_image_url": "https://pbs.twimg.com/profile_images/1945506638892355584/vuuDoKyJ_normal.jpg",
        "protected": false,
        "public_metrics": {
          "followers_count": 400,
          "following_count": 695,
          "like_count": 6276,
          "listed_count": 0,
          "media_count": 217,
          "tweet_count": 1882
        },
        "username": "Cheese_Ghostfox",
        "verified": false
      },
      {
        "created_at": "2024-08-01T16:10:08.000Z",
        "description": "最好的朋友@gxdnkj//成为顶天立地的人",
        "entities": {
          "description": {
            "mentions": [
              {
                "end": 12,
                "start": 5,
                "username": "gxdnkj"
              }
            ]
          }
        },
        "id": "1819042830549204992",
        "location": "星球博物馆–东亚区–525号废物展示厅",
        "name": "祀萨",
        "pinned_tweet_id": "1911072778977198333",
        "profile_image_url": "https://pbs.twimg.com/profile_images/1957040513787564032/bpG3Elmm_normal.jpg",
        "protected": false,
        "public_metrics": {
          "followers_count": 119,
          "following_count": 62,
          "like_count": 3908,
          "listed_count": 3,
          "media_count": 23,
          "tweet_count": 1760
        },
        "username": "ss3996418",
        "verified": false
      }
    ]
  }
}