{
  "data": {
    "article": {},
    "attachments": {},
    "author_id": "1620506107306479617",
    "conversation_id": "1970321866561855735",
    "created_at": "2025-09-23T08:31:03.000Z",
    "edit_controls": {
      "editable_until": "2025-09-23T09:31:03.000Z",
      "edits_remaining": 5,
      "is_edit_eligible": false
    },
    "edit_history_tweet_ids": [
      "1970405537209864247"
    ],
    "entities": {
      "mentions": [
        {
          "end": 15,
          "id": "1883888910838943744",
          "start": 0,
          "username": "xingmang114514"
        }
      ]
    },
    "geo": {},
    "id": "1970405537209864247",
    "in_reply_to_user_id": "1883888910838943744",
    "lang": "zh",
    "note_tweet": {
      "entities": {}
    },
    "possibly_sensitive": false,
    "public_metrics": {
      "bookmark_count": 0,
      "impression_count": 0,
      "like_count": 0,
      "quote_count": 0,
      "reply_count": 0,
      "retweet_count": 0
    },
    "referenced_tweets": [
      {
        "id": "1970321866561855735",
        "type": "replied_to"
      }
    ],
    "reply_settings": "everyone",
    "text": "@xingmang114514 请啥都没用了😱"
  },
  "includes": {
    "tweets": [
      {
        "article": {},
        "attachments": {},
        "author_id": "1620506107306479617",
        "conversation_id": "1970321866561855735",
        "created_at": "2025-09-23T08:31:03.000Z",
        "edit_controls": {
          "editable_until": "2025-09-23T09:31:03.000Z",
          "edits_remaining": 5,
          "is_edit_eligible": false
        },
        "edit_history_tweet_ids": [
          "1970405537209864247"
        ],
        "entities": {
          "mentions": [
            {
              "end": 15,
              "id": "1883888910838943744",
              "start": 0,
              "username": "xingmang114514"
            }
          ]
        },
        "geo": {},
        "id": "1970405537209864247",
        "in_reply_to_user_id": "1883888910838943744",
        "lang": "zh",
        "note_tweet": {
          "entities": {}
        },
        "possibly_sensitive": false,
        "public_metrics": {
          "bookmark_count": 0,
          "impression_count": 0,
          "like_count": 0,
          "quote_count": 0,
          "reply_count": 0,
          "retweet_count": 0
        },
        "referenced_tweets": [
          {
            "id": "1970321866561855735",
            "type": "replied_to"
          }
        ],
        "reply_settings": "everyone",
        "text": "@xingmang114514 请啥都没用了😱"
      },
      {
        "article": {},
        "attachments": {},
        "author_id": "1883888910838943744",
        "conversation_id": "1970321866561855735",
        "created_at": "2025-09-23T02:58:34.000Z",
        "edit_controls": {
          "editable_until": "2025-09-23T03:58:34.000Z",
          "edits_remaining": 5,
          "is_edit_eligible": true
        },
        "edit_history_tweet_ids": [
          "1970321866561855735"
        ],
        "entities": {},
        "geo": {},
        "id": "1970321866561855735",
        "lang": "zh",
        "note_tweet": {
          "entities": {}
        },
        "possibly_sensitive": false,
        "public_metrics": {
          "bookmark_count": 0,
          "impression_count": 605,
          "like_count": 23,
          "quote_count": 0,
          "reply_count": 5,
          "retweet_count": 2
        },
        "reply_settings": "everyone",
        "text": "一想到今晚广东的流浪猫都要变成飞基悲就想笑（"
      }
    ],
    "users": [
      {
        "created_at": "2023-01-31T19:36:01.000Z",
        "description": "欠拟合狐狐与您同在~ 丨☯Survivalist 生存主義者 醫學/電子工程學🆙 丨INTP–T丨MtX幽默无证药娘(?)🏳️‍⚧️丨私人實驗室「靈狐製作所」創始人(建設ing…)🧬丨拒絕鑑政辨經❌/超友好🥰丨燦若花火的生命，无法用只言片语概括丨裡推 @HEX_Ghostfox丨恋人 @HydrogenNeko",
        "entities": {
          "description": {
            "mentions": [
              {
                "end": 139,
                "start": 126,
                "username": "HEX_Ghostfox"
              },
              {
                "end": 156,
                "start": 143,
                "username": "HydrogenNeko"
              }
            ]
          }
        },
        "id": "1620506107306479617",
        "location": "-0.15m",
        "name": "☯️🧬霊狐製作所 公式ツイッター🏳️‍⚧️",
        "pinned_tweet_id": "1919548841357148382",
        "profile_image_url": "https://pbs.twimg.com/profile_images/1945506638892355584/vuuDoKyJ_normal.jpg",
        "protected": false,
        "public_metrics": {
          "followers_count": 548,
          "following_count": 888,
          "like_count": 7785,
          "listed_count": 2,
          "media_count": 239,
          "tweet_count": 2259
        },
        "username": "Cheese_Ghostfox",
        "verified": false
      },
      {
        "created_at": "2025-01-27T14:45:01.000Z",
        "description": "初中生/苦命oc人\n也是B站vup：凯芒KeMon✨\n稿件堆放处，抽象文案发电中\n群号：474838612\n\n即🌟刻🌟轮🌟回🌟❗",
        "id": "1883888910838943744",
        "name": "凯芒KeMon♿️→hf",
        "pinned_tweet_id": "1969653483797430623",
        "profile_image_url": "https://pbs.twimg.com/profile_images/1883889039226630144/wpWMJ3N5_normal.jpg",
        "protected": false,
        "public_metrics": {
          "followers_count": 482,
          "following_count": 416,
          "like_count": 431,
          "listed_count": 0,
          "media_count": 23,
          "tweet_count": 143
        },
        "username": "xingmang114514",
        "verified": false
      }
    ]
  }
}