{
  "data": {
    "article": {},
    "attachments": {},
    "author_id": "1620506107306479617",
    "conversation_id": "1986942288296026447",
    "created_at": "2025-11-08T00:28:37.000Z",
    "edit_controls": {
      "editable_until": "2025-11-08T01:28:37.000Z",
      "edits_remaining": 5,
      "is_edit_eligible": false
    },
    "edit_history_tweet_ids": [
      "1986953973916705092"
    ],
    "entities": {
      "mentions": [
        {
          "end": 12,
          "id": "1913309341735956480",
          "start": 0,
          "username": "yingyang_FW"
        }
      ]
    },
    "geo": {},
    "id": "1986953973916705092",
    "in_reply_to_user_id": "1913309341735956480",
    "lang": "zh",
    "note_tweet": {
      "entities": {}
    },
    "possibly_sensitive": false,
    "public_metrics": {
      "bookmark_count": 0,
      "impression_count": 0,
      "like_count": 0,
      "quote_count": 0,
      "reply_count": 0,
      "retweet_count": 0
    },
    "referenced_tweets": [
      {
        "id": "1986942288296026447",
        "type": "replied_to"
      }
    ],
    "reply_settings": "everyone",
    "text": "@yingyang_FW 另外您扎的这个部位目测是腓骨长肌上端部，肌肉注射一般不会采用这个位置，有几条静脉与神经会从这经过，肌肉也不够肥厚容易戳到骨头，一定喜欢扎腿的话建议试试股外侧肌"
  },
  "includes": {
    "media": [
      {
        "height": 1152,
        "media_key": "3_1986942280289185792",
        "public_metrics": {},
        "type": "photo",
        "url": "https://pbs.twimg.com/media/G5MJegXXcAA1D5T.jpg",
        "width": 2048
      },
      {
        "height": 1152,
        "media_key": "3_1986942284995182592",
        "public_metrics": {},
        "type": "photo",
        "url": "https://pbs.twimg.com/media/G5MJex5XQAAzJVX.jpg",
        "width": 2048
      }
    ],
    "tweets": [
      {
        "article": {},
        "attachments": {},
        "author_id": "1620506107306479617",
        "conversation_id": "1986942288296026447",
        "created_at": "2025-11-08T00:28:37.000Z",
        "edit_controls": {
          "editable_until": "2025-11-08T01:28:37.000Z",
          "edits_remaining": 5,
          "is_edit_eligible": false
        },
        "edit_history_tweet_ids": [
          "1986953973916705092"
        ],
        "entities": {
          "mentions": [
            {
              "end": 12,
              "id": "1913309341735956480",
              "start": 0,
              "username": "yingyang_FW"
            }
          ]
        },
        "geo": {},
        "id": "1986953973916705092",
        "in_reply_to_user_id": "1913309341735956480",
        "lang": "zh",
        "note_tweet": {
          "entities": {}
        },
        "possibly_sensitive": false,
        "public_metrics": {
          "bookmark_count": 0,
          "impression_count": 0,
          "like_count": 0,
          "quote_count": 0,
          "reply_count": 0,
          "retweet_count": 0
        },
        "referenced_tweets": [
          {
            "id": "1986942288296026447",
            "type": "replied_to"
          }
        ],
        "reply_settings": "everyone",
        "text": "@yingyang_FW 另外您扎的这个部位目测是腓骨长肌上端部，肌肉注射一般不会采用这个位置，有几条静脉与神经会从这经过，肌肉也不够肥厚容易戳到骨头，一定喜欢扎腿的话建议试试股外侧肌"
      },
      {
        "article": {},
        "attachments": {
          "media_keys": [
            "3_1986942280289185792",
            "3_1986942284995182592"
          ]
        },
        "author_id": "1913309341735956480",
        "conversation_id": "1986942288296026447",
        "created_at": "2025-11-07T23:42:11.000Z",
        "edit_controls": {
          "editable_until": "2025-11-08T00:42:11.000Z",
          "edits_remaining": 5,
          "is_edit_eligible": true
        },
        "edit_history_tweet_ids": [
          "1986942288296026447"
        ],
        "entities": {
          "urls": [
            {
              "display_url": "pic.x.com/z2aZMu0bYn",
              "end": 57,
              "expanded_url": "https://x.com/yingyang_FW/status/1986942288296026447/photo/1",
              "media_key": "3_1986942280289185792",
              "start": 34,
              "url": "https://t.co/z2aZMu0bYn"
            },
            {
              "display_url": "pic.x.com/z2aZMu0bYn",
              "end": 57,
              "expanded_url": "https://x.com/yingyang_FW/status/1986942288296026447/photo/1",
              "media_key": "3_1986942284995182592",
              "start": 34,
              "url": "https://t.co/z2aZMu0bYn"
            }
          ]
        },
        "geo": {},
        "id": "1986942288296026447",
        "lang": "zh",
        "note_tweet": {
          "entities": {}
        },
        "possibly_sensitive": false,
        "public_metrics": {
          "bookmark_count": 0,
          "impression_count": 10,
          "like_count": 2,
          "quote_count": 0,
          "reply_count": 2,
          "retweet_count": 0
        },
        "reply_settings": "everyone",
        "text": "第一针日雌，不太顺利。\n在右腿外侧扎的，扎了五针才找到正确的位置。 https://t.co/z2aZMu0bYn"
      }
    ],
    "users": [
      {
        "created_at": "2023-01-31T19:36:01.000Z",
        "description": "单线程狐狐与您同在~ 丨☯Survivalist 生存主義者 醫學/電子工程學🆙 丨INTP–T丨MtX无证药娘(?)🏳️‍⚧️丨私人實驗室「靈狐製作所」創始人(建設ing…)🧬丨技術加速主義/超友好🥰丨燦若花火的生命，无法用只言片语概括丨裡推 @HEX_Ghostfox丨恋人 @YekaseSuiso2022",
        "entities": {
          "description": {
            "mentions": [
              {
                "end": 136,
                "start": 123,
                "username": "HEX_Ghostfox"
              },
              {
                "end": 156,
                "start": 140,
                "username": "YekaseSuiso2022"
              }
            ]
          }
        },
        "id": "1620506107306479617",
        "location": "-0.15m",
        "name": "☯️🧬暗号通貨戦士霊狐🏳️‍⚧️",
        "pinned_tweet_id": "1971908706771304723",
        "profile_image_url": "https://pbs.twimg.com/profile_images/1984625831894016000/RhpiuO0V_normal.jpg",
        "protected": false,
        "public_metrics": {
          "followers_count": 694,
          "following_count": 1051,
          "like_count": 9425,
          "listed_count": 2,
          "media_count": 289,
          "tweet_count": 2733
        },
        "username": "Cheese_Ghostfox",
        "verified": false
      },
      {
        "created_at": "2025-04-18T19:11:33.000Z",
        "description": "mtf｜同类互fo｜166cm 59kg｜无证含糖｜生日2010.11.28｜互fo｜🍥:2025.6.30｜欢迎找我扩列｜想在推上交朋友｜傻傻的｜社恐｜不会聊天｜常驻昆明｜已炸柜｜亲爱的老公@ling_feng64507",
        "entities": {
          "description": {
            "mentions": [
              {
                "end": 111,
                "start": 96,
                "username": "ling_feng64507"
              }
            ]
          },
          "url": {
            "urls": [
              {
                "display_url": "t.me/yyyjhfw",
                "end": 23,
                "expanded_url": "http://t.me/yyyjhfw",
                "start": 0,
                "url": "https://t.co/0mRJesmFT5"
              }
            ]
          }
        },
        "id": "1913309341735956480",
        "location": "谁知道呢",
        "name": "营养要均衡🍥",
        "profile_image_url": "https://pbs.twimg.com/profile_images/1950147286937587715/jqqsbiqt_normal.jpg",
        "protected": false,
        "public_metrics": {
          "followers_count": 1123,
          "following_count": 749,
          "like_count": 14651,
          "listed_count": 1,
          "media_count": 127,
          "tweet_count": 1129
        },
        "url": "https://t.co/0mRJesmFT5",
        "username": "yingyang_FW",
        "verified": false
      }
    ]
  }
}