{
  "data": {
    "article": {},
    "attachments": {},
    "author_id": "1620506107306479617",
    "conversation_id": "2045207732320600192",
    "created_at": "2026-04-17T18:28:16.000Z",
    "edit_controls": {
      "editable_until": "2026-04-17T19:28:16.000Z",
      "edits_remaining": 5,
      "is_edit_eligible": true
    },
    "edit_history_tweet_ids": [
      "2045207732320600192"
    ],
    "entities": {},
    "geo": {},
    "id": "2045207732320600192",
    "lang": "zh",
    "note_tweet": {
      "entities": {},
      "text": "为什么...\n明明已经平复了,尽最大努力去遗忘了,不在那种激烈可怖的状态里了\n但是那种微妙的悲伤还是不能放过我呢...\n做任何事都会不可控地,被侵入性思维引领到那个,最害怕的区域\n然后再被那个惨烈的既定事实把四肢百骸,每一个关节,每一段随意肌与交感神经,凌迟,攥紧,加以一种强烈电击般的刺痛,一种近似于生长痛的,骨头缝被拧进一根钻头一样的紧张感\n只求这种症状能放过我..."
    },
    "possibly_sensitive": false,
    "public_metrics": {
      "bookmark_count": 0,
      "impression_count": 0,
      "like_count": 0,
      "quote_count": 0,
      "reply_count": 0,
      "retweet_count": 0
    },
    "reply_settings": "everyone",
    "text": "为什么...\n明明已经平复了,尽最大努力去遗忘了,不在那种激烈可怖的状态里了\n但是那种微妙的悲伤还是不能放过我呢...\n做任何事都会不可控地,被侵入性思维引领到那个,最害怕的区域"
  },
  "includes": {
    "tweets": [
      {
        "article": {},
        "attachments": {},
        "author_id": "1620506107306479617",
        "conversation_id": "2045207732320600192",
        "created_at": "2026-04-17T18:28:16.000Z",
        "edit_controls": {
          "editable_until": "2026-04-17T19:28:16.000Z",
          "edits_remaining": 5,
          "is_edit_eligible": true
        },
        "edit_history_tweet_ids": [
          "2045207732320600192"
        ],
        "entities": {},
        "geo": {},
        "id": "2045207732320600192",
        "lang": "zh",
        "note_tweet": {
          "entities": {},
          "text": "为什么...\n明明已经平复了,尽最大努力去遗忘了,不在那种激烈可怖的状态里了\n但是那种微妙的悲伤还是不能放过我呢...\n做任何事都会不可控地,被侵入性思维引领到那个,最害怕的区域\n然后再被那个惨烈的既定事实把四肢百骸,每一个关节,每一段随意肌与交感神经,凌迟,攥紧,加以一种强烈电击般的刺痛,一种近似于生长痛的,骨头缝被拧进一根钻头一样的紧张感\n只求这种症状能放过我..."
        },
        "possibly_sensitive": false,
        "public_metrics": {
          "bookmark_count": 0,
          "impression_count": 0,
          "like_count": 0,
          "quote_count": 0,
          "reply_count": 0,
          "retweet_count": 0
        },
        "reply_settings": "everyone",
        "text": "为什么...\n明明已经平复了,尽最大努力去遗忘了,不在那种激烈可怖的状态里了\n但是那种微妙的悲伤还是不能放过我呢...\n做任何事都会不可控地,被侵入性思维引领到那个,最害怕的区域"
      }
    ],
    "users": [
      {
        "created_at": "2023-01-31T19:36:01.000Z",
        "description": "狐狐「霧開川 望」与您同在~ 丨☯Survivalist 生存主義者 醫學/電子工程學🆙 丨INTP–T丨非二元 MtFutanari 无证药娘(?)🏳️‍⚧️丨She/Her丨私人實驗室「靈狐製作所」創始人(建設ing…)🧬丨技術加速主義/超友好🥰丨「願愛與健康常伴汝身」丨裡推@HEX_Ghostfox",
        "entities": {
          "description": {
            "mentions": [
              {
                "end": 153,
                "start": 140,
                "username": "HEX_Ghostfox"
              }
            ]
          },
          "url": {
            "urls": [
              {
                "display_url": "github.com/CheeseGhostfox",
                "end": 23,
                "expanded_url": "https://github.com/CheeseGhostfox",
                "start": 0,
                "url": "https://t.co/COn8ugIjyQ"
              }
            ]
          }
        },
        "id": "1620506107306479617",
        "location": "-0.15m",
        "name": "☯️🧬霊狐製作所 公式ツイッター",
        "pinned_tweet_id": "2029634600147018027",
        "profile_image_url": "https://pbs.twimg.com/profile_images/2014282980437434368/FxOUZWSV_normal.jpg",
        "protected": false,
        "public_metrics": {
          "followers_count": 1387,
          "following_count": 1465,
          "like_count": 16776,
          "listed_count": 4,
          "media_count": 581,
          "tweet_count": 5309
        },
        "url": "https://t.co/COn8ugIjyQ",
        "username": "Cheese_Ghostfox",
        "verified": true
      }
    ]
  }
}